LICENSE
README.md
setup.py
pipely/__init__.py
pipely/__main__.py
pipely/version.py
pipely.egg-info/PKG-INFO
pipely.egg-info/SOURCES.txt
pipely.egg-info/dependency_links.txt
pipely.egg-info/requires.txt
pipely.egg-info/top_level.txt
pipely/config/config.py
pipely/engine/__init__.py
pipely/engine/trigger_from_class.py
pipely/engine/trigger_from_yaml.py