Metadata-Version: 2.1
Name: pipely
Version: 0.3.0
Summary: Light pipeline framework.
Home-page: https://github.com/5x12/pipely
Author: 5x12, sergbakh, notrurs, benoitconnan
License: MIT
Download-URL: https://github.com/5x12/pipely/archive/{version}.tar.gz
Keywords: PIPELY,PIPELINE,PIPE
Platform: UNKNOWN
Classifier: Development Status :: 3 - Alpha
Classifier: Intended Audience :: Developers
Classifier: License :: OSI Approved :: MIT License
Classifier: Programming Language :: Python :: 3.6
Requires-Python: >=3.8
License-File: LICENSE
